mxcp/__main__.py
mxcp/py.typed
mxcp/plugins/__init__.py
mxcp/plugins/_types.py
mxcp/plugins/base.py
mxcp/runtime/__init__.py
mxcp/sdk/__init__.py
mxcp/sdk/models.py
mxcp/sdk/audit/__init__.py
mxcp/sdk/audit/logger.py
mxcp/sdk/audit/models.py
mxcp/sdk/audit/query.py
mxcp/sdk/audit/redaction.py
mxcp/sdk/audit/writer.py
mxcp/sdk/audit/backends/__init__.py
mxcp/sdk/audit/backends/jsonl.py
mxcp/sdk/audit/backends/noop.py
mxcp/sdk/auth/__init__.py
mxcp/sdk/auth/auth_service.py
mxcp/sdk/auth/context.py
mxcp/sdk/auth/contracts.py
mxcp/sdk/auth/middleware.py
mxcp/sdk/auth/models.py
mxcp/sdk/auth/session_manager.py
mxcp/sdk/auth/storage.py
mxcp/sdk/auth/url_utils.py
mxcp/sdk/auth/providers/__init__.py
mxcp/sdk/auth/providers/atlassian.py
mxcp/sdk/auth/providers/dummy.py
mxcp/sdk/auth/providers/github.py
mxcp/sdk/auth/providers/google.py
mxcp/sdk/auth/providers/keycloak.py
mxcp/sdk/auth/providers/salesforce.py
mxcp/sdk/core/__init__.py
mxcp/sdk/core/version.py
mxcp/sdk/core/analytics/__init__.py
mxcp/sdk/core/config/__init__.py
mxcp/sdk/core/config/loader.py
mxcp/sdk/core/config/models.py
mxcp/sdk/core/config/plugins.py
mxcp/sdk/core/config/processor.py
mxcp/sdk/core/config/resolvers/__init__.py
mxcp/sdk/core/config/resolvers/env.py
mxcp/sdk/core/config/resolvers/file.py
mxcp/sdk/core/config/resolvers/onepassword.py
mxcp/sdk/core/config/resolvers/vault.py
mxcp/sdk/duckdb/__init__.py
mxcp/sdk/duckdb/extension_loader.py
mxcp/sdk/duckdb/models.py
mxcp/sdk/duckdb/plugin_loader.py
mxcp/sdk/duckdb/runtime.py
mxcp/sdk/duckdb/secret_injection.py
mxcp/sdk/duckdb/session.py
mxcp/sdk/evals/__init__.py
mxcp/sdk/evals/_types.py
mxcp/sdk/evals/executor.py
mxcp/sdk/executor/__init__.py
mxcp/sdk/executor/context.py
mxcp/sdk/executor/interfaces.py
mxcp/sdk/executor/models.py
mxcp/sdk/executor/plugins/__init__.py
mxcp/sdk/executor/plugins/duckdb.py
mxcp/sdk/executor/plugins/python.py
mxcp/sdk/executor/plugins/python_plugin/__init__.py
mxcp/sdk/executor/plugins/python_plugin/loader.py
mxcp-0.11.0.dist-info/licenses/LICENSE
mxcp-0.11.0.dist-info/METADATA
mxcp-0.11.0.dist-info/WHEEL
mxcp-0.11.0.dist-info/entry_points.txt
mxcp-0.11.0.dist-info/top_level.txt
mxcp-0.11.0.dist-info/RECORD
