Metadata-Version: 2.4
Name: mxcp
Version: 0.11.0
Summary: Enterprise MCP framework for building production AI tools with SQL/Python, featuring security, audit trails, and policy enforcement
Author-email: RAW Labs SA <mxcp@raw-labs.com>
License-Expression: BUSL-1.1
Requires-Python: >=3.10
License-File: LICENSE
Requires-Dist: mcp<1.26,>=1.22
Requires-Dist: aiohttp>=3.8.0
Requires-Dist: aiofiles>=23.2.1
Requires-Dist: starlette>=0.27.0
Requires-Dist: duckdb>=1.4.1
Requires-Dist: pandas>=2.0.0
Requires-Dist: pyyaml>=6.0.1
Requires-Dist: jinja2>=3.1.3
Requires-Dist: makefun
Requires-Dist: cel-python>=0.2.0
Requires-Dist: httpx>=0.28.0
Requires-Dist: cryptography>=41.0.0
Requires-Dist: click>=8.1.7
Requires-Dist: posthog>=3.0.0
Requires-Dist: dbt-core>=1.6.0
Requires-Dist: dbt-duckdb>=1.6.0
Requires-Dist: opentelemetry-api>=1.24.0
Requires-Dist: opentelemetry-sdk>=1.24.0
Requires-Dist: opentelemetry-exporter-otlp-proto-http>=1.24.0
Requires-Dist: fastapi>=0.110.0
Requires-Dist: uvicorn[standard]>=0.27.0
Requires-Dist: psutil>=5.9.0
Provides-Extra: dev
Requires-Dist: pytest; extra == "dev"
Requires-Dist: pytest-asyncio; extra == "dev"
Requires-Dist: pytest-cov; extra == "dev"
Requires-Dist: pytest-mock; extra == "dev"
Requires-Dist: pytest-timeout; extra == "dev"
Requires-Dist: aioresponses; extra == "dev"
Requires-Dist: black; extra == "dev"
Requires-Dist: ruff; extra == "dev"
Requires-Dist: mypy; extra == "dev"
Requires-Dist: types-PyYAML; extra == "dev"
Requires-Dist: types-psutil; extra == "dev"
Requires-Dist: pandas-stubs; extra == "dev"
Requires-Dist: build; extra == "dev"
Requires-Dist: twine; extra == "dev"
Provides-Extra: vault
Requires-Dist: hvac>=2.0.0; extra == "vault"
Provides-Extra: onepassword
Requires-Dist: onepassword-sdk>=0.3.0; extra == "onepassword"
Provides-Extra: all
Requires-Dist: hvac>=2.0.0; extra == "all"
Requires-Dist: onepassword-sdk>=0.3.0; extra == "all"
Requires-Dist: pytest; extra == "all"
Requires-Dist: pytest-asyncio; extra == "all"
Requires-Dist: pytest-cov; extra == "all"
Requires-Dist: pytest-mock; extra == "all"
Requires-Dist: pytest-timeout; extra == "all"
Requires-Dist: aioresponses; extra == "all"
Requires-Dist: black; extra == "all"
Requires-Dist: ruff; extra == "all"
Requires-Dist: mypy; extra == "all"
Requires-Dist: types-psutil; extra == "all"
Requires-Dist: pandas-stubs; extra == "all"
Requires-Dist: build; extra == "all"
Requires-Dist: twine; extra == "all"
Dynamic: license-file
